<?xml version="1.0" encoding="UTF-8"?>
<objects serializationModel="Studio.02.00.00">
	<object class="AudioFile" id="{3330add8-60b0-42ea-a7c1-6f6d1a5b208d}">
		<property name="assetPath">
			<value>18403__inferno__xplosm.wav</value>
		</property>
		<property name="frequencyInKHz">
			<value>44.0999985</value>
		</property>
		<property name="channelCount">
			<value>1</value>
		</property>
		<property name="length">
			<value>1.3710204081632653</value>
		</property>
		<relationship name="masterAssetFolder">
			<destination>{56af671b-92bf-4028-ab58-01331c0e8228}</destination>
		</relationship>
	</object>
</objects>
